pelican/plugins/add_css_classes/__init__.py
pelican/plugins/add_css_classes/add_css_classes.py
pelican/plugins/add_css_classes/test_add_css_classes.py
pelican_add_css_classes-1.0.4.dist-info/WHEEL
pelican_add_css_classes-1.0.4.dist-info/METADATA
pelican_add_css_classes-1.0.4.dist-info/RECORD
