Metadata-Version: 2.1
Name: pelican-add-css-classes
Version: 1.0.4
Summary: Adds CSS classes to html tags in Pelican documents
Home-page: https://github.com/johanvergeer/pelican-add-css-classes
License: MIT
Keywords: pelican,plugin
Author: Johan Vergeer
Author-email: johanvergeer@gmail.com
Requires-Python: >=3.6,<4.0
Classifier: Development Status :: 5 - Production/Stable
Classifier: Environment :: Console
Classifier: Framework :: Pelican
Classifier: Framework :: Pelican :: Plugins
Classifier: Intended Audience :: Developers
Classifier: License :: OSI Approved :: MIT License
Classifier: Operating System :: OS Independent
Classifier: Programming Language :: Python
Classifier: Programming Language :: Python :: 3
Classifier: Programming Language :: Python :: 3.6
Classifier: Programming Language :: Python :: 3.7
Classifier: Programming Language :: Python :: 3.8
Classifier: Topic :: Internet :: WWW/HTTP
Classifier: Topic :: Software Development :: Libraries :: Python Modules
Provides-Extra: markdown
Requires-Dist: beautifulsoup4 (>=4.8,<5.0)
Requires-Dist: markdown (>=3.1.1,<4.0.0); extra == "markdown"
Requires-Dist: pelican (>=4.2,<5.0)
Requires-Dist: toml (>=0.10.0,<0.11.0)
Project-URL: Repository, https://github.com/johanvergeer/pelican-add-css-classes
